{"source/main.ptx": ["my-great-book"], "source/frontmatter.ptx": ["frontmatter"], "source/ch-gearup.ptx": ["ch-gearup"], "source/sec-belhavenmcs.ptx": ["sec-belhaven-math-intro"], "source/sec-successfuls.ptx": ["sec-successfuls"], "source/sec-careers.ptx": ["sec-career"], "source/sec-sets.ptx": ["sec-sets"], "source/sec-pascaltriangle.ptx": ["sec-pascaltriangle"], "source/sec-logicpuzzle.ptx": ["sec-logicpuzzle"], "source/sec-arguments.ptx": ["sec-arguments"], "source/sec-graphtheory.ptx": ["sec-graphtheory"], "source/sec-fourcolors.ptx": ["sec-fourcolors"], "source/sec-history.ptx": ["sec-history"], "source/ch-worldofcalculus.ptx": ["ch-worldofcalculus-title"], "source/file-worldofcalculus/sec-harnessinf.ptx": ["sec-harnessinf"], "source/file-worldofcalculus/sec-newtonleibniz.ptx": ["sec-newtonleibniz"], "source/file-worldofcalculus/sec-archimedes.ptx": ["sec-archimedes"], "source/file-worldofcalculus/sec-calcinmovies.ptx": ["sec-calcinmovies"], "source/file-worldofcalculus/sec-ratesofchange.ptx": ["sec-ratesofchange"], "source/file-worldofcalculus/sec-surfaces.ptx": ["sec-surfaces"], "source/file-worldofcalculus/sec-polarcoords.ptx": ["sec-polarcoords"], "source/ch-worldsofalgebra.ptx": ["ch-worldsofalgebra-title"], "source/file-worldsofalgebra/sec-pipealgebra.ptx": ["sec-pipe-algebra"], "source/file-worldsofalgebra/sec-groups.ptx": ["sec-groups"], "source/ch-discovery.ptx": ["ch-chapter-discovery"], "source/file-discovery/sec-biggestprime.ptx": ["sec-biggestprime"], "source/backmatter.ptx": ["backmatter"]}